{
  "trade_date": "2026.05.11",
  "etf_code": "009804",
  "etf_name": "聯邦台精彩50",
  "issuer": "",
  "market": "TWSE",
  "source": "issuer_pcf",
  "source_url": "https://www.usitc.com.tw/CustCenter/BuyBackList",
  "pcf_identity": {
    "ok": true,
    "method": "visible_context_match",
    "target_etf_code": "009804",
    "target_etf_name": "聯邦台精彩50",
    "matched_context": "聯邦台灣精彩50ETF基金 ( 009804 )",
    "reason": "Page title/header/selected option visibly matches target ETF."
  },
  "pcf_meta": {
    "trade_date": "2026.05.11",
    "fund_nav": 0.0,
    "outstanding_units": 0.0,
    "unit_diff": 0.0,
    "nav_per_unit": 0.0,
    "creation_unit": 0.0
  },
  "holdings": [
    {
      "stock_code": "1216",
      "stock_name": "統一",
      "shares": 244219.0,
      "weight_pct": 0.714,
      "close": 0.0,
      "market_value": 0.0,
      "source_table": "table_3"
    },
    {
      "stock_code": "1301",
      "stock_name": "臺塑",
      "shares": 208090.0,
      "weight_pct": 0.4035,
      "close": 0.0,
      "market_value": 0.0,
      "source_table": "table_3"
    },
    {
      "stock_code": "1303",
      "stock_name": "南亞",
      "shares": 244376.0,
      "weight_pct": 0.8648,
      "close": 0.0,
      "market_value": 0.0,
      "source_table": "table_3"
    },
    {
      "stock_code": "2002",
      "stock_name": "中鋼",
      "shares": 554379.0,
      "weight_pct": 0.4152,
      "close": 0.0,
      "market_value": 0.0,
      "source_table": "table_3"
    },
    {
      "stock_code": "2059",
      "stock_name": "川湖",
      "shares": 2814.0,
      "weight_pct": 0.5979,
      "close": 0.0,
      "market_value": 0.0,
      "source_table": "table_3"
    },
    {
      "stock_code": "2207",
      "stock_name": "和泰車",
      "shares": 13879.0,
      "weight_pct": 0.27,
      "close": 0.0,
      "market_value": 0.0,
      "source_table": "table_3"
    },
    {
      "stock_code": "2301",
      "stock_name": "光寶科",
      "shares": 96338.0,
      "weight_pct": 0.785,
      "close": 0.0,
      "market_value": 0.0,
      "source_table": "table_3"
    },
    {
      "stock_code": "2303",
      "stock_name": "聯電",
      "shares": 578062.0,
      "weight_pct": 2.108,
      "close": 0.0,
      "market_value": 0.0,
      "source_table": "table_3"
    },
    {
      "stock_code": "2308",
      "stock_name": "台達電",
      "shares": 96283.0,
      "weight_pct": 8.4605,
      "close": 0.0,
      "market_value": 0.0,
      "source_table": "table_3"
    },
    {
      "stock_code": "2317",
      "stock_name": "鴻海",
      "shares": 606902.0,
      "weight_pct": 6.0602,
      "close": 0.0,
      "market_value": 0.0,
      "source_table": "table_3"
    },
    {
      "stock_code": "2327",
      "stock_name": "國巨*",
      "shares": 76998.0,
      "weight_pct": 1.1963,
      "close": 0.0,
      "market_value": 0.0,
      "source_table": "table_3"
    },
    {
      "stock_code": "2330",
      "stock_name": "台積電",
      "shares": 304380.0,
      "weight_pct": 27.8405,
      "close": 0.0,
      "market_value": 0.0,
      "source_table": "table_3"
    },
    {
      "stock_code": "2344",
      "stock_name": "華邦電",
      "shares": 154762.0,
      "weight_pct": 0.6614,
      "close": 0.0,
      "market_value": 0.0,
      "source_table": "table_3"
    },
    {
      "stock_code": "2345",
      "stock_name": "智邦",
      "shares": 24586.0,
      "weight_pct": 2.3323,
      "close": 0.0,
      "market_value": 0.0,
      "source_table": "table_3"
    },
    {
      "stock_code": "2357",
      "stock_name": "華碩",
      "shares": 33874.0,
      "weight_pct": 0.8794,
      "close": 0.0,
      "market_value": 0.0,
      "source_table": "table_3"
    },
    {
      "stock_code": "2360",
      "stock_name": "致茂",
      "shares": 18291.0,
      "weight_pct": 1.6292,
      "close": 0.0,
      "market_value": 0.0,
      "source_table": "table_3"
    },
    {
      "stock_code": "2368",
      "stock_name": "金像電",
      "shares": 17072.0,
      "weight_pct": 0.9069,
      "close": 0.0,
      "market_value": 0.0,
      "source_table": "table_3"
    },
    {
      "stock_code": "2382",
      "stock_name": "廣達",
      "shares": 130874.0,
      "weight_pct": 1.7799,
      "close": 0.0,
      "market_value": 0.0,
      "source_table": "table_3"
    },
    {
      "stock_code": "2383",
      "stock_name": "台光電",
      "shares": 14204.0,
      "weight_pct": 2.6948,
      "close": 0.0,
      "market_value": 0.0,
      "source_table": "table_3"
    },
    {
      "stock_code": "2395",
      "stock_name": "研華",
      "shares": 22775.0,
      "weight_pct": 0.4335,
      "close": 0.0,
      "market_value": 0.0,
      "source_table": "table_3"
    },
    {
      "stock_code": "2408",
      "stock_name": "南亞科",
      "shares": 55703.0,
      "weight_pct": 0.6096,
      "close": 0.0,
      "market_value": 0.0,
      "source_table": "table_3"
    },
    {
      "stock_code": "2412",
      "stock_name": "中華電",
      "shares": 189276.0,
      "weight_pct": 1.0319,
      "close": 0.0,
      "market_value": 0.0,
      "source_table": "table_3"
    },
    {
      "stock_code": "2449",
      "stock_name": "京元電子",
      "shares": 53944.0,
      "weight_pct": 0.6701,
      "close": 0.0,
      "market_value": 0.0,
      "source_table": "table_3"
    },
    {
      "stock_code": "2454",
      "stock_name": "聯發科",
      "shares": 72310.0,
      "weight_pct": 10.4841,
      "close": 0.0,
      "market_value": 0.0,
      "source_table": "table_3"
    },
    {
      "stock_code": "2603",
      "stock_name": "長榮",
      "shares": 53892.0,
      "weight_pct": 0.4553,
      "close": 0.0,
      "market_value": 0.0,
      "source_table": "table_3"
    },
    {
      "stock_code": "2880",
      "stock_name": "華南金",
      "shares": 461417.0,
      "weight_pct": 0.6137,
      "close": 0.0,
      "market_value": 0.0,
      "source_table": "table_3"
    },
    {
      "stock_code": "2881",
      "stock_name": "富邦金",
      "shares": 413862.0,
      "weight_pct": 1.5985,
      "close": 0.0,
      "market_value": 0.0,
      "source_table": "table_3"
    },
    {
      "stock_code": "2882",
      "stock_name": "國泰金",
      "shares": 464382.0,
      "weight_pct": 1.4839,
      "close": 0.0,
      "market_value": 0.0,
      "source_table": "table_3"
    },
    {
      "stock_code": "2883",
      "stock_name": "凱基金",
      "shares": 782190.0,
      "weight_pct": 0.7154,
      "close": 0.0,
      "market_value": 0.0,
      "source_table": "table_3"
    },
    {
      "stock_code": "2884",
      "stock_name": "玉山金",
      "shares": 761224.0,
      "weight_pct": 0.9881,
      "close": 0.0,
      "market_value": 0.0,
      "source_table": "table_3"
    },
    {
      "stock_code": "2885",
      "stock_name": "元大金",
      "shares": 540436.0,
      "weight_pct": 1.2196,
      "close": 0.0,
      "market_value": 0.0,
      "source_table": "table_3"
    },
    {
      "stock_code": "2886",
      "stock_name": "兆豐金",
      "shares": 585795.0,
      "weight_pct": 0.9406,
      "close": 0.0,
      "market_value": 0.0,
      "source_table": "table_3"
    },
    {
      "stock_code": "2887",
      "stock_name": "台新新光金",
      "shares": 1140363.0,
      "weight_pct": 1.084,
      "close": 0.0,
      "market_value": 0.0,
      "source_table": "table_3"
    },
    {
      "stock_code": "2890",
      "stock_name": "永豐金",
      "shares": 628765.0,
      "weight_pct": 0.7785,
      "close": 0.0,
      "market_value": 0.0,
      "source_table": "table_3"
    },
    {
      "stock_code": "2891",
      "stock_name": "中信金",
      "shares": 875735.0,
      "weight_pct": 1.9728,
      "close": 0.0,
      "market_value": 0.0,
      "source_table": "table_3"
    },
    {
      "stock_code": "2892",
      "stock_name": "第一金",
      "shares": 538194.0,
      "weight_pct": 0.6341,
      "close": 0.0,
      "market_value": 0.0,
      "source_table": "table_3"
    },
    {
      "stock_code": "3008",
      "stock_name": "大立光",
      "shares": 4761.0,
      "weight_pct": 0.4887,
      "close": 0.0,
      "market_value": 0.0,
      "source_table": "table_3"
    },
    {
      "stock_code": "3017",
      "stock_name": "奇鋐",
      "shares": 16072.0,
      "weight_pct": 1.5695,
      "close": 0.0,
      "market_value": 0.0,
      "source_table": "table_3"
    },
    {
      "stock_code": "3037",
      "stock_name": "欣興",
      "shares": 66168.0,
      "weight_pct": 2.1619,
      "close": 0.0,
      "market_value": 0.0,
      "source_table": "table_3"
    },
    {
      "stock_code": "3045",
      "stock_name": "台灣大",
      "shares": 70104.0,
      "weight_pct": 0.308,
      "close": 0.0,
      "market_value": 0.0,
      "source_table": "table_3"
    },
    {
      "stock_code": "3231",
      "stock_name": "緯創",
      "shares": 151724.0,
      "weight_pct": 0.8878,
      "close": 0.0,
      "market_value": 0.0,
      "source_table": "table_3"
    },
    {
      "stock_code": "3653",
      "stock_name": "健策",
      "shares": 4144.0,
      "weight_pct": 0.6041,
      "close": 0.0,
      "market_value": 0.0,
      "source_table": "table_3"
    },
    {
      "stock_code": "3661",
      "stock_name": "世芯-KY",
      "shares": 3939.0,
      "weight_pct": 0.7693,
      "close": 0.0,
      "market_value": 0.0,
      "source_table": "table_3"
    },
    {
      "stock_code": "3711",
      "stock_name": "日月光投控",
      "shares": 162701.0,
      "weight_pct": 3.3533,
      "close": 0.0,
      "market_value": 0.0,
      "source_table": "table_3"
    },
    {
      "stock_code": "4904",
      "stock_name": "遠傳電信",
      "shares": 87976.0,
      "weight_pct": 0.337,
      "close": 0.0,
      "market_value": 0.0,
      "source_table": "table_3"
    },
    {
      "stock_code": "5880",
      "stock_name": "合庫金",
      "shares": 519012.0,
      "weight_pct": 0.4778,
      "close": 0.0,
      "market_value": 0.0,
      "source_table": "table_3"
    },
    {
      "stock_code": "6505",
      "stock_name": "台塑化",
      "shares": 59056.0,
      "weight_pct": 0.125,
      "close": 0.0,
      "market_value": 0.0,
      "source_table": "table_3"
    },
    {
      "stock_code": "6669",
      "stock_name": "緯穎",
      "shares": 5134.0,
      "weight_pct": 1.0663,
      "close": 0.0,
      "market_value": 0.0,
      "source_table": "table_3"
    },
    {
      "stock_code": "6919",
      "stock_name": "康霈*",
      "shares": 49292.0,
      "weight_pct": 0.2048,
      "close": 0.0,
      "market_value": 0.0,
      "source_table": "table_3"
    },
    {
      "stock_code": "7769",
      "stock_name": "鴻勁",
      "shares": 2829.0,
      "weight_pct": 0.6554,
      "close": 0.0,
      "market_value": 0.0,
      "source_table": "table_3"
    }
  ]
}
